{"schemaVersion":2,"pokemonId":"pokemon:0339-barboach","source":{"retrievedAt":"2026-07-23","sourceRevision":"bf4c47ac82c33b330e33d98b8882d1cedb2f53e7","sourceUrls":["https://github.com/PokeAPI/sprites/tree/bf4c47ac82c33b330e33d98b8882d1cedb2f53e7","https://github.com/PokeAPI/sprites/blob/bf4c47ac82c33b330e33d98b8882d1cedb2f53e7/LICENCE.txt"],"licenseStatus":"doubtful","requiredCredits":["The Pokémon Company for official image contents, as declared by the source repository.","PokéAPI and the named community artists where a candidate comes from a fan-made collection."],"notes":["The source repository applies CC0 while also declaring image copyright owned by The Pokémon Company.","That conflict does not establish clear authority to redistribute the images in this public repository.","The repository owner explicitly directed publication of four compact battle sprites per species; rights remain doubtful and the runtime does not load them."]},"sourceUrlBase":"https://raw.githubusercontent.com/PokeAPI/sprites/bf4c47ac82c33b330e33d98b8882d1cedb2f53e7/","rightsCatalogPath":"../../../catalogs/asset-rights.json","mediaImportedCount":4,"statusSummary":{"approved":0,"pending":0,"doubtful":42,"rejected":0,"quarantined":0},"entries":[{"id":"58623827b46577452d3526ce54045e373cc6d28d","collection":"pokeapi-default","perspective":"front","variation":"normal","animated":false,"extension":"png","bytes":492,"sourceRepositoryPath":"sprites/pokemon/339.png","rightsPolicyId":"official-image-rights-unclear","status":"doubtful","originalName":"339.png","proposedName":"0339--barboach--pokeapi-default--front--normal--58623827.png","localQuarantine":{"variantId":"front-normal","sourceRelativePath":"339.png","localOnly":true,"relativePrivatePath":".private/pokemon-canonical/0339-barboach/sprites/0339-barboach--pokeapi-default--front--normal.png","sha256":"8383c70eedd6536fe0da6f2e43a6b08c0539b7604461452a2c597b452c08f562","bytes":492,"width":96,"height":96,"animated":false,"frameCount":1,"transparency":"present-or-palette-dependent"},"repositoryAsset":{"variantId":"front-normal","repositoryPath":"sprites/0339-barboach--pokeapi-default--front--normal.png","sha256":"8383c70eedd6536fe0da6f2e43a6b08c0539b7604461452a2c597b452c08f562","bytes":492,"width":96,"height":96,"animated":false,"frameCount":1,"ownerAuthorizedAt":"2026-07-23","rightsStatus":"doubtful"}},{"id":"e2e7149fa16a28bce8b7169441e023eeac03a622","collection":"pokeapi-back","perspective":"front","variation":"normal","animated":false,"extension":"png","bytes":490,"sourceRepositoryPath":"sprites/pokemon/back/339.png","rightsPolicyId":"official-image-rights-unclear","status":"doubtful","originalName":"339.png","proposedName":"0339--barboach--pokeapi-back--front--normal--e2e7149f.png","localQuarantine":{"variantId":"back-normal","sourceRelativePath":"back/339.png","localOnly":true,"relativePrivatePath":".private/pokemon-canonical/0339-barboach/sprites/0339-barboach--pokeapi-default--back--normal.png","sha256":"3fa0fa32f6b2a71db43523353b785b2a89bf20efb35a5b0722b5b5cef97c7cfd","bytes":490,"width":96,"height":96,"animated":false,"frameCount":1,"transparency":"present-or-palette-dependent"},"repositoryAsset":{"variantId":"back-normal","repositoryPath":"sprites/0339-barboach--pokeapi-default--back--normal.png","sha256":"3fa0fa32f6b2a71db43523353b785b2a89bf20efb35a5b0722b5b5cef97c7cfd","bytes":490,"width":96,"height":96,"animated":false,"frameCount":1,"ownerAuthorizedAt":"2026-07-23","rightsStatus":"doubtful"}},{"id":"6d9be915b800630bad7e4e4b07a03512ba343920","collection":"pokeapi-back-shiny","perspective":"front","variation":"shiny","animated":false,"extension":"png","bytes":491,"sourceRepositoryPath":"sprites/pokemon/back/shiny/339.png","rightsPolicyId":"official-image-rights-unclear","status":"doubtful","originalName":"339.png","proposedName":"0339--barboach--pokeapi-back-shiny--front--shiny--6d9be915.png","localQuarantine":{"variantId":"back-shiny","sourceRelativePath":"back/shiny/339.png","localOnly":true,"relativePrivatePath":".private/pokemon-canonical/0339-barboach/sprites/0339-barboach--pokeapi-default--back--shiny.png","sha256":"f38f9a8644f45185707f392985bbe74cb422806d9761fee8f6522f622c2989da","bytes":491,"width":96,"height":96,"animated":false,"frameCount":1,"transparency":"present-or-palette-dependent"},"repositoryAsset":{"variantId":"back-shiny","repositoryPath":"sprites/0339-barboach--pokeapi-default--back--shiny.png","sha256":"f38f9a8644f45185707f392985bbe74cb422806d9761fee8f6522f622c2989da","bytes":491,"width":96,"height":96,"animated":false,"frameCount":1,"ownerAuthorizedAt":"2026-07-23","rightsStatus":"doubtful"}},{"id":"13110a913125f153c5d4898f0a6b458cbf54c82e","collection":"other-dream-world","perspective":"front","variation":"normal","animated":false,"extension":"svg","bytes":11950,"sourceRepositoryPath":"sprites/pokemon/other/dream-world/339.svg","rightsPolicyId":"official-image-rights-unclear","status":"doubtful","originalName":"339.svg","proposedName":"0339--barboach--other-dream-world--front--normal--13110a91.svg"},{"id":"e9108e9b1f478bd4806f879055691f46ac84ec0d","collection":"other-home","perspective":"front","variation":"normal","animated":false,"extension":"png","bytes":78076,"sourceRepositoryPath":"sprites/pokemon/other/home/339.png","rightsPolicyId":"official-image-rights-unclear","status":"doubtful","originalName":"339.png","proposedName":"0339--barboach--other-home--front--normal--e9108e9b.png"},{"id":"0eeae174687c5d231c3fd3ce8be7b1e3a92580e4","collection":"other-home-shiny","perspective":"front","variation":"shiny","animated":false,"extension":"png","bytes":76323,"sourceRepositoryPath":"sprites/pokemon/other/home/shiny/339.png","rightsPolicyId":"official-image-rights-unclear","status":"doubtful","originalName":"339.png","proposedName":"0339--barboach--other-home-shiny--front--shiny--0eeae174.png"},{"id":"8aad47a55bee4ba91b0a14f8040ab6eab7ddc93c","collection":"other-official-artwork","perspective":"front","variation":"normal","animated":false,"extension":"png","bytes":85603,"sourceRepositoryPath":"sprites/pokemon/other/official-artwork/339.png","rightsPolicyId":"official-image-rights-unclear","status":"doubtful","originalName":"339.png","proposedName":"0339--barboach--other-official-artwork--front--normal--8aad47a5.png"},{"id":"e0d6f615e912503cfb6a181313b8c373e4cb4f69","collection":"other-official-artwork-shiny","perspective":"front","variation":"shiny","animated":false,"extension":"png","bytes":90137,"sourceRepositoryPath":"sprites/pokemon/other/official-artwork/shiny/339.png","rightsPolicyId":"official-image-rights-unclear","status":"doubtful","originalName":"339.png","proposedName":"0339--barboach--other-official-artwork-shiny--front--shiny--e0d6f615.png"},{"id":"a739d42821916fa0a9ce521fa64bb0aeb16e0a07","collection":"pokeapi-shiny","perspective":"front","variation":"shiny","animated":false,"extension":"png","bytes":493,"sourceRepositoryPath":"sprites/pokemon/shiny/339.png","rightsPolicyId":"official-image-rights-unclear","status":"doubtful","originalName":"339.png","proposedName":"0339--barboach--pokeapi-shiny--front--shiny--a739d428.png","localQuarantine":{"variantId":"front-shiny","sourceRelativePath":"shiny/339.png","localOnly":true,"relativePrivatePath":".private/pokemon-canonical/0339-barboach/sprites/0339-barboach--pokeapi-default--front--shiny.png","sha256":"1bb159475839770ffc40a4839e0d7cdf4ea61314ea824f1986009d01534911a8","bytes":493,"width":96,"height":96,"animated":false,"frameCount":1,"transparency":"present-or-palette-dependent"},"repositoryAsset":{"variantId":"front-shiny","repositoryPath":"sprites/0339-barboach--pokeapi-default--front--shiny.png","sha256":"1bb159475839770ffc40a4839e0d7cdf4ea61314ea824f1986009d01534911a8","bytes":493,"width":96,"height":96,"animated":false,"frameCount":1,"ownerAuthorizedAt":"2026-07-23","rightsStatus":"doubtful"}},{"id":"843ef7594afb99f601ce0f16a7c385c736f0b06c","collection":"generation-iii-emerald","perspective":"front","variation":"normal","animated":false,"extension":"png","bytes":795,"sourceRepositoryPath":"sprites/pokemon/versions/generation-iii/emerald/339.png","rightsPolicyId":"official-image-rights-unclear","status":"doubtful","originalName":"339.png","proposedName":"0339--barboach--generation-iii-emerald--front--normal--843ef759.png"},{"id":"9ebcd3482edbe0507c64c84c5843ac496b1b88f2","collection":"generation-iii-emerald-shiny","perspective":"front","variation":"shiny","animated":false,"extension":"png","bytes":843,"sourceRepositoryPath":"sprites/pokemon/versions/generation-iii/emerald/shiny/339.png","rightsPolicyId":"official-image-rights-unclear","status":"doubtful","originalName":"339.png","proposedName":"0339--barboach--generation-iii-emerald-shiny--front--shiny--9ebcd348.png"},{"id":"84bdc313c497483841900613ba5ef32d3a5b532a","collection":"generation-iii-ruby-sapphire","perspective":"front","variation":"normal","animated":false,"extension":"png","bytes":607,"sourceRepositoryPath":"sprites/pokemon/versions/generation-iii/ruby-sapphire/339.png","rightsPolicyId":"official-image-rights-unclear","status":"doubtful","originalName":"339.png","proposedName":"0339--barboach--generation-iii-ruby-sapphire--front--normal--84bdc313.png"},{"id":"cd5cb2662a7da33eee13a809bd461eec6b07d59e","collection":"generation-iii-ruby-sapphire-back","perspective":"back","variation":"normal","animated":false,"extension":"png","bytes":581,"sourceRepositoryPath":"sprites/pokemon/versions/generation-iii/ruby-sapphire/back/339.png","rightsPolicyId":"official-image-rights-unclear","status":"doubtful","originalName":"339.png","proposedName":"0339--barboach--generation-iii-ruby-sapphire-back--back--normal--cd5cb266.png"},{"id":"18f219e672767b52b391ed7fb85f819a6c24ca68","collection":"generation-iii-ruby-sapphire-back-shiny","perspective":"back","variation":"shiny","animated":false,"extension":"png","bytes":580,"sourceRepositoryPath":"sprites/pokemon/versions/generation-iii/ruby-sapphire/back/shiny/339.png","rightsPolicyId":"official-image-rights-unclear","status":"doubtful","originalName":"339.png","proposedName":"0339--barboach--generation-iii-ruby-sapphire-back-shiny--back--shiny--18f219e6.png"},{"id":"b0c3d67f85069786ce6c35ea713dce061d57254d","collection":"generation-iii-ruby-sapphire-shiny","perspective":"front","variation":"shiny","animated":false,"extension":"png","bytes":606,"sourceRepositoryPath":"sprites/pokemon/versions/generation-iii/ruby-sapphire/shiny/339.png","rightsPolicyId":"official-image-rights-unclear","status":"doubtful","originalName":"339.png","proposedName":"0339--barboach--generation-iii-ruby-sapphire-shiny--front--shiny--b0c3d67f.png"},{"id":"85b97337c9f418f1029e293b5cd9d8b0e5e8b8c9","collection":"generation-iv-diamond-pearl","perspective":"front","variation":"normal","animated":false,"extension":"png","bytes":753,"sourceRepositoryPath":"sprites/pokemon/versions/generation-iv/diamond-pearl/339.png","rightsPolicyId":"official-image-rights-unclear","status":"doubtful","originalName":"339.png","proposedName":"0339--barboach--generation-iv-diamond-pearl--front--normal--85b97337.png"},{"id":"664700f87a9a5b951b6d824a447b729dbb523a1a","collection":"generation-iv-diamond-pearl-back","perspective":"back","variation":"normal","animated":false,"extension":"png","bytes":881,"sourceRepositoryPath":"sprites/pokemon/versions/generation-iv/diamond-pearl/back/339.png","rightsPolicyId":"official-image-rights-unclear","status":"doubtful","originalName":"339.png","proposedName":"0339--barboach--generation-iv-diamond-pearl-back--back--normal--664700f8.png"},{"id":"286caaca0e95ff17262f0ac14405ac877c28e181","collection":"generation-iv-diamond-pearl-back-shiny","perspective":"back","variation":"shiny","animated":false,"extension":"png","bytes":878,"sourceRepositoryPath":"sprites/pokemon/versions/generation-iv/diamond-pearl/back/shiny/339.png","rightsPolicyId":"official-image-rights-unclear","status":"doubtful","originalName":"339.png","proposedName":"0339--barboach--generation-iv-diamond-pearl-back-shiny--back--shiny--286caaca.png"},{"id":"fcb03099942ecd7692295c0860f265b19a56d094","collection":"generation-iv-diamond-pearl-shiny","perspective":"front","variation":"shiny","animated":false,"extension":"png","bytes":749,"sourceRepositoryPath":"sprites/pokemon/versions/generation-iv/diamond-pearl/shiny/339.png","rightsPolicyId":"official-image-rights-unclear","status":"doubtful","originalName":"339.png","proposedName":"0339--barboach--generation-iv-diamond-pearl-shiny--front--shiny--fcb03099.png"},{"id":"94cf1195d5c0d0613b47b36510eb75f8253ea904","collection":"generation-iv-heartgold-soulsilver","perspective":"front","variation":"normal","animated":false,"extension":"png","bytes":664,"sourceRepositoryPath":"sprites/pokemon/versions/generation-iv/heartgold-soulsilver/339.png","rightsPolicyId":"official-image-rights-unclear","status":"doubtful","originalName":"339.png","proposedName":"0339--barboach--generation-iv-heartgold-soulsilver--front--normal--94cf1195.png"},{"id":"3a6036a8fec7b95c818f5190064170bfbdbc53df","collection":"generation-iv-heartgold-soulsilver-back","perspective":"back","variation":"normal","animated":false,"extension":"png","bytes":865,"sourceRepositoryPath":"sprites/pokemon/versions/generation-iv/heartgold-soulsilver/back/339.png","rightsPolicyId":"official-image-rights-unclear","status":"doubtful","originalName":"339.png","proposedName":"0339--barboach--generation-iv-heartgold-soulsilver-back--back--normal--3a6036a8.png"},{"id":"273fd5daeb13b758dab69dd7762981e7fc7ba917","collection":"generation-iv-heartgold-soulsilver-back-shiny","perspective":"back","variation":"shiny","animated":false,"extension":"png","bytes":857,"sourceRepositoryPath":"sprites/pokemon/versions/generation-iv/heartgold-soulsilver/back/shiny/339.png","rightsPolicyId":"official-image-rights-unclear","status":"doubtful","originalName":"339.png","proposedName":"0339--barboach--generation-iv-heartgold-soulsilver-back-shiny--back--shiny--273fd5da.png"},{"id":"9942d2d811dbf8fb64c595b0f46afe243c67694b","collection":"generation-iv-heartgold-soulsilver-shiny","perspective":"front","variation":"shiny","animated":false,"extension":"png","bytes":651,"sourceRepositoryPath":"sprites/pokemon/versions/generation-iv/heartgold-soulsilver/shiny/339.png","rightsPolicyId":"official-image-rights-unclear","status":"doubtful","originalName":"339.png","proposedName":"0339--barboach--generation-iv-heartgold-soulsilver-shiny--front--shiny--9942d2d8.png"},{"id":"2ed04aba1de2a4bcb6ac98d22aa9348f8af4e3f1","collection":"generation-iv-platinum","perspective":"front","variation":"normal","animated":false,"extension":"png","bytes":485,"sourceRepositoryPath":"sprites/pokemon/versions/generation-iv/platinum/339.png","rightsPolicyId":"official-image-rights-unclear","status":"doubtful","originalName":"339.png","proposedName":"0339--barboach--generation-iv-platinum--front--normal--2ed04aba.png"},{"id":"415a4a09ff898c499b81944f0676164fcc0637e1","collection":"generation-iv-platinum-back","perspective":"back","variation":"normal","animated":false,"extension":"png","bytes":923,"sourceRepositoryPath":"sprites/pokemon/versions/generation-iv/platinum/back/339.png","rightsPolicyId":"official-image-rights-unclear","status":"doubtful","originalName":"339.png","proposedName":"0339--barboach--generation-iv-platinum-back--back--normal--415a4a09.png"},{"id":"6241f55b689f0f3e1363ec21698ae6deffb224b0","collection":"generation-iv-platinum-back-shiny","perspective":"back","variation":"shiny","animated":false,"extension":"png","bytes":912,"sourceRepositoryPath":"sprites/pokemon/versions/generation-iv/platinum/back/shiny/339.png","rightsPolicyId":"official-image-rights-unclear","status":"doubtful","originalName":"339.png","proposedName":"0339--barboach--generation-iv-platinum-back-shiny--back--shiny--6241f55b.png"},{"id":"e25618dde0ec410a4c113b916844b62eee22dbf3","collection":"generation-iv-platinum-shiny","perspective":"front","variation":"shiny","animated":false,"extension":"png","bytes":485,"sourceRepositoryPath":"sprites/pokemon/versions/generation-iv/platinum/shiny/339.png","rightsPolicyId":"official-image-rights-unclear","status":"doubtful","originalName":"339.png","proposedName":"0339--barboach--generation-iv-platinum-shiny--front--shiny--e25618dd.png"},{"id":"a03f1b01e7b57c6a36799e64932abf7eacc815c6","collection":"generation-ix-scarlet-violet","perspective":"front","variation":"normal","animated":false,"extension":"png","bytes":11912,"sourceRepositoryPath":"sprites/pokemon/versions/generation-ix/scarlet-violet/339.png","rightsPolicyId":"official-image-rights-unclear","status":"doubtful","originalName":"339.png","proposedName":"0339--barboach--generation-ix-scarlet-violet--front--normal--a03f1b01.png"},{"id":"58623827b46577452d3526ce54045e373cc6d28d","collection":"generation-v-black-white","perspective":"front","variation":"normal","animated":false,"extension":"png","bytes":492,"sourceRepositoryPath":"sprites/pokemon/versions/generation-v/black-white/339.png","rightsPolicyId":"official-image-rights-unclear","status":"doubtful","originalName":"339.png","proposedName":"0339--barboach--generation-v-black-white--front--normal--58623827.png"},{"id":"e2e7149fa16a28bce8b7169441e023eeac03a622","collection":"generation-v-black-white-back","perspective":"back","variation":"normal","animated":false,"extension":"png","bytes":490,"sourceRepositoryPath":"sprites/pokemon/versions/generation-v/black-white/back/339.png","rightsPolicyId":"official-image-rights-unclear","status":"doubtful","originalName":"339.png","proposedName":"0339--barboach--generation-v-black-white-back--back--normal--e2e7149f.png"},{"id":"6d9be915b800630bad7e4e4b07a03512ba343920","collection":"generation-v-black-white-back-shiny","perspective":"back","variation":"shiny","animated":false,"extension":"png","bytes":491,"sourceRepositoryPath":"sprites/pokemon/versions/generation-v/black-white/back/shiny/339.png","rightsPolicyId":"official-image-rights-unclear","status":"doubtful","originalName":"339.png","proposedName":"0339--barboach--generation-v-black-white-back-shiny--back--shiny--6d9be915.png"},{"id":"a739d42821916fa0a9ce521fa64bb0aeb16e0a07","collection":"generation-v-black-white-shiny","perspective":"front","variation":"shiny","animated":false,"extension":"png","bytes":493,"sourceRepositoryPath":"sprites/pokemon/versions/generation-v/black-white/shiny/339.png","rightsPolicyId":"official-image-rights-unclear","status":"doubtful","originalName":"339.png","proposedName":"0339--barboach--generation-v-black-white-shiny--front--shiny--a739d428.png"},{"id":"1bb9076c56f15a3b05ad4654dbb8613cd5fa7f8f","collection":"generation-v-icons","perspective":"front","variation":"normal","animated":false,"extension":"png","bytes":235,"sourceRepositoryPath":"sprites/pokemon/versions/generation-v/icons/339.png","rightsPolicyId":"official-image-rights-unclear","status":"doubtful","originalName":"339.png","proposedName":"0339--barboach--generation-v-icons--front--normal--1bb9076c.png"},{"id":"bf46276295eaf4875be80c866f5fe8cbadb4c7fe","collection":"generation-vi-omegaruby-alphasapphire","perspective":"front","variation":"normal","animated":false,"extension":"png","bytes":2336,"sourceRepositoryPath":"sprites/pokemon/versions/generation-vi/omegaruby-alphasapphire/339.png","rightsPolicyId":"official-image-rights-unclear","status":"doubtful","originalName":"339.png","proposedName":"0339--barboach--generation-vi-omegaruby-alphasapphire--front--normal--bf462762.png"},{"id":"4487a93d44ff12534f8a79013980df5d6a4f22c0","collection":"generation-vi-omegaruby-alphasapphire-shiny","perspective":"front","variation":"shiny","animated":false,"extension":"png","bytes":2317,"sourceRepositoryPath":"sprites/pokemon/versions/generation-vi/omegaruby-alphasapphire/shiny/339.png","rightsPolicyId":"official-image-rights-unclear","status":"doubtful","originalName":"339.png","proposedName":"0339--barboach--generation-vi-omegaruby-alphasapphire-shiny--front--shiny--4487a93d.png"},{"id":"a091e5f49a8a17d2c336b8f4925249492373cd5d","collection":"generation-vi-x-y","perspective":"front","variation":"normal","animated":false,"extension":"png","bytes":1378,"sourceRepositoryPath":"sprites/pokemon/versions/generation-vi/x-y/339.png","rightsPolicyId":"official-image-rights-unclear","status":"doubtful","originalName":"339.png","proposedName":"0339--barboach--generation-vi-x-y--front--normal--a091e5f4.png"},{"id":"04d5dec52675a2fa352776866d4be80b697de998","collection":"generation-vi-x-y-shiny","perspective":"front","variation":"shiny","animated":false,"extension":"png","bytes":1614,"sourceRepositoryPath":"sprites/pokemon/versions/generation-vi/x-y/shiny/339.png","rightsPolicyId":"official-image-rights-unclear","status":"doubtful","originalName":"339.png","proposedName":"0339--barboach--generation-vi-x-y-shiny--front--shiny--04d5dec5.png"},{"id":"aeece3b849bfbeaa97c80324e0911978ef6cd57e","collection":"generation-vii-icons","perspective":"front","variation":"normal","animated":false,"extension":"png","bytes":229,"sourceRepositoryPath":"sprites/pokemon/versions/generation-vii/icons/339.png","rightsPolicyId":"official-image-rights-unclear","status":"doubtful","originalName":"339.png","proposedName":"0339--barboach--generation-vii-icons--front--normal--aeece3b8.png"},{"id":"9699267010415ea10a93897e0578a8ac6b68c480","collection":"generation-vii-ultra-sun-ultra-moon","perspective":"front","variation":"normal","animated":false,"extension":"png","bytes":3530,"sourceRepositoryPath":"sprites/pokemon/versions/generation-vii/ultra-sun-ultra-moon/339.png","rightsPolicyId":"official-image-rights-unclear","status":"doubtful","originalName":"339.png","proposedName":"0339--barboach--generation-vii-ultra-sun-ultra-moon--front--normal--96992670.png"},{"id":"91d95e4cc65a20a2589d6944c8ddcdee9ebddac6","collection":"generation-vii-ultra-sun-ultra-moon-shiny","perspective":"front","variation":"shiny","animated":false,"extension":"png","bytes":3525,"sourceRepositoryPath":"sprites/pokemon/versions/generation-vii/ultra-sun-ultra-moon/shiny/339.png","rightsPolicyId":"official-image-rights-unclear","status":"doubtful","originalName":"339.png","proposedName":"0339--barboach--generation-vii-ultra-sun-ultra-moon-shiny--front--shiny--91d95e4c.png"},{"id":"b90fa10cf52fb05d84f7e44cf67c0a2182e5e1d7","collection":"generation-viii-brilliant-diamond-shining-pearl","perspective":"front","variation":"normal","animated":false,"extension":"png","bytes":12313,"sourceRepositoryPath":"sprites/pokemon/versions/generation-viii/brilliant-diamond-shining-pearl/339.png","rightsPolicyId":"official-image-rights-unclear","status":"doubtful","originalName":"339.png","proposedName":"0339--barboach--generation-viii-brilliant-diamond-shining-pearl--front--normal--b90fa10c.png"},{"id":"b321dc8c47ba6b53e91578470d6f490ae7d52304","collection":"generation-viii-icons","perspective":"front","variation":"normal","animated":false,"extension":"png","bytes":267,"sourceRepositoryPath":"sprites/pokemon/versions/generation-viii/icons/339.png","rightsPolicyId":"official-image-rights-unclear","status":"doubtful","originalName":"339.png","proposedName":"0339--barboach--generation-viii-icons--front--normal--b321dc8c.png"}]}
