{"schemaVersion":2,"pokemonId":"pokemon:0992-iron-hands","source":{"retrievedAt":"2026-07-23","sourceRevision":"bf4c47ac82c33b330e33d98b8882d1cedb2f53e7","sourceUrls":["https://github.com/PokeAPI/sprites/tree/bf4c47ac82c33b330e33d98b8882d1cedb2f53e7","https://github.com/PokeAPI/sprites/blob/bf4c47ac82c33b330e33d98b8882d1cedb2f53e7/LICENCE.txt"],"licenseStatus":"doubtful","requiredCredits":["The Pokémon Company for official image contents, as declared by the source repository.","PokéAPI and the named community artists where a candidate comes from a fan-made collection."],"notes":["The source repository applies CC0 while also declaring image copyright owned by The Pokémon Company.","That conflict does not establish clear authority to redistribute the images in this public repository.","The repository owner explicitly directed publication of four compact battle sprites per species; rights remain doubtful and the runtime does not load them."]},"sourceUrlBase":"https://raw.githubusercontent.com/PokeAPI/sprites/bf4c47ac82c33b330e33d98b8882d1cedb2f53e7/","rightsCatalogPath":"../../../catalogs/asset-rights.json","mediaImportedCount":4,"statusSummary":{"approved":0,"pending":2,"doubtful":10,"rejected":0,"quarantined":0},"entries":[{"id":"70c2bc4e9191696a0875ee193e6d0c0cae71280f","collection":"pokeapi-default","perspective":"front","variation":"normal","animated":false,"extension":"png","bytes":3631,"sourceRepositoryPath":"sprites/pokemon/992.png","rightsPolicyId":"official-image-rights-unclear","status":"doubtful","originalName":"992.png","proposedName":"0992--iron-hands--pokeapi-default--front--normal--70c2bc4e.png","localQuarantine":{"variantId":"front-normal","sourceRelativePath":"992.png","localOnly":true,"relativePrivatePath":".private/pokemon-canonical/0992-iron-hands/sprites/0992-iron-hands--pokeapi-default--front--normal.png","sha256":"40a9fea8fbdd9e960b4c4b99fdbd1686e0f4ca5ae9b7ad2e2e1994322ea69f4c","bytes":3631,"width":96,"height":96,"animated":false,"frameCount":1,"transparency":"present-or-palette-dependent"},"repositoryAsset":{"variantId":"front-normal","repositoryPath":"sprites/0992-iron-hands--pokeapi-default--front--normal.png","sha256":"40a9fea8fbdd9e960b4c4b99fdbd1686e0f4ca5ae9b7ad2e2e1994322ea69f4c","bytes":3631,"width":96,"height":96,"animated":false,"frameCount":1,"ownerAuthorizedAt":"2026-07-23","rightsStatus":"doubtful"}},{"id":"645731029b7e1f551d5ece9ce28bbf785a7936ca","collection":"pokeapi-back","perspective":"front","variation":"normal","animated":false,"extension":"png","bytes":2266,"sourceRepositoryPath":"sprites/pokemon/back/992.png","rightsPolicyId":"official-image-rights-unclear","status":"doubtful","originalName":"992.png","proposedName":"0992--iron-hands--pokeapi-back--front--normal--64573102.png","localQuarantine":{"variantId":"back-normal","sourceRelativePath":"back/992.png","localOnly":true,"relativePrivatePath":".private/pokemon-canonical/0992-iron-hands/sprites/0992-iron-hands--pokeapi-default--back--normal.png","sha256":"8672f51f92160bbae31f553f0f7ff07569526cd2ac5b772fe02785972d6d5809","bytes":2266,"width":96,"height":96,"animated":false,"frameCount":1,"transparency":"present-or-palette-dependent"},"repositoryAsset":{"variantId":"back-normal","repositoryPath":"sprites/0992-iron-hands--pokeapi-default--back--normal.png","sha256":"8672f51f92160bbae31f553f0f7ff07569526cd2ac5b772fe02785972d6d5809","bytes":2266,"width":96,"height":96,"animated":false,"frameCount":1,"ownerAuthorizedAt":"2026-07-23","rightsStatus":"doubtful"}},{"id":"edff484a1ab785f9a40225c99373286707d8c456","collection":"pokeapi-back-shiny","perspective":"front","variation":"shiny","animated":false,"extension":"png","bytes":2132,"sourceRepositoryPath":"sprites/pokemon/back/shiny/992.png","rightsPolicyId":"official-image-rights-unclear","status":"doubtful","originalName":"992.png","proposedName":"0992--iron-hands--pokeapi-back-shiny--front--shiny--edff484a.png","localQuarantine":{"variantId":"back-shiny","sourceRelativePath":"back/shiny/992.png","localOnly":true,"relativePrivatePath":".private/pokemon-canonical/0992-iron-hands/sprites/0992-iron-hands--pokeapi-default--back--shiny.png","sha256":"720202e8382589567dd6a11cd3d24c7973bd7cd4c07c148eb829645aecbca8b9","bytes":2132,"width":96,"height":96,"animated":false,"frameCount":1,"transparency":"present-or-palette-dependent"},"repositoryAsset":{"variantId":"back-shiny","repositoryPath":"sprites/0992-iron-hands--pokeapi-default--back--shiny.png","sha256":"720202e8382589567dd6a11cd3d24c7973bd7cd4c07c148eb829645aecbca8b9","bytes":2132,"width":96,"height":96,"animated":false,"frameCount":1,"ownerAuthorizedAt":"2026-07-23","rightsStatus":"doubtful"}},{"id":"79058915f73db8c68e11776f9e190b7c018c1a18","collection":"other-dream-world","perspective":"front","variation":"normal","animated":false,"extension":"svg","bytes":251753,"sourceRepositoryPath":"sprites/pokemon/other/dream-world/992.svg","rightsPolicyId":"official-image-rights-unclear","status":"doubtful","originalName":"992.svg","proposedName":"0992--iron-hands--other-dream-world--front--normal--79058915.svg"},{"id":"50c3bfcf6b198741dc1527777f4d67b9c2c2d597","collection":"other-home","perspective":"front","variation":"normal","animated":false,"extension":"png","bytes":145461,"sourceRepositoryPath":"sprites/pokemon/other/home/992.png","rightsPolicyId":"official-image-rights-unclear","status":"doubtful","originalName":"992.png","proposedName":"0992--iron-hands--other-home--front--normal--50c3bfcf.png"},{"id":"3fcdbb64c758cc025d809e205f340bf468a3b2cd","collection":"other-home-shiny","perspective":"front","variation":"shiny","animated":false,"extension":"png","bytes":148834,"sourceRepositoryPath":"sprites/pokemon/other/home/shiny/992.png","rightsPolicyId":"official-image-rights-unclear","status":"doubtful","originalName":"992.png","proposedName":"0992--iron-hands--other-home-shiny--front--shiny--3fcdbb64.png"},{"id":"cc2701d896b7ba521bd8af7bf8398c5506ccc97c","collection":"other-official-artwork","perspective":"front","variation":"normal","animated":false,"extension":"png","bytes":147280,"sourceRepositoryPath":"sprites/pokemon/other/official-artwork/992.png","rightsPolicyId":"official-image-rights-unclear","status":"doubtful","originalName":"992.png","proposedName":"0992--iron-hands--other-official-artwork--front--normal--cc2701d8.png"},{"id":"bd15ec8aac36cc050105f77df061a032fd85dba2","collection":"other-official-artwork-shiny","perspective":"front","variation":"shiny","animated":false,"extension":"png","bytes":129365,"sourceRepositoryPath":"sprites/pokemon/other/official-artwork/shiny/992.png","rightsPolicyId":"official-image-rights-unclear","status":"doubtful","originalName":"992.png","proposedName":"0992--iron-hands--other-official-artwork-shiny--front--shiny--bd15ec8a.png"},{"id":"d7cd25afdaefa63157b22ea7a686b94921c7bdb6","collection":"pokeapi-shiny","perspective":"front","variation":"shiny","animated":false,"extension":"png","bytes":3586,"sourceRepositoryPath":"sprites/pokemon/shiny/992.png","rightsPolicyId":"official-image-rights-unclear","status":"doubtful","originalName":"992.png","proposedName":"0992--iron-hands--pokeapi-shiny--front--shiny--d7cd25af.png","localQuarantine":{"variantId":"front-shiny","sourceRelativePath":"shiny/992.png","localOnly":true,"relativePrivatePath":".private/pokemon-canonical/0992-iron-hands/sprites/0992-iron-hands--pokeapi-default--front--shiny.png","sha256":"f806995e34f21bf0b76dd04c174d0972045d4801f3d9c3f26d0edf0291ab2f7f","bytes":3586,"width":96,"height":96,"animated":false,"frameCount":1,"transparency":"present-or-palette-dependent"},"repositoryAsset":{"variantId":"front-shiny","repositoryPath":"sprites/0992-iron-hands--pokeapi-default--front--shiny.png","sha256":"f806995e34f21bf0b76dd04c174d0972045d4801f3d9c3f26d0edf0291ab2f7f","bytes":3586,"width":96,"height":96,"animated":false,"frameCount":1,"ownerAuthorizedAt":"2026-07-23","rightsStatus":"doubtful"}},{"id":"cea8f260859c8273a868281e953b9d6e65ad8023","collection":"generation-ix-scarlet-violet","perspective":"front","variation":"normal","animated":false,"extension":"png","bytes":33518,"sourceRepositoryPath":"sprites/pokemon/versions/generation-ix/scarlet-violet/992.png","rightsPolicyId":"official-image-rights-unclear","status":"doubtful","originalName":"992.png","proposedName":"0992--iron-hands--generation-ix-scarlet-violet--front--normal--cea8f260.png"},{"id":"70c2bc4e9191696a0875ee193e6d0c0cae71280f","collection":"generation-v-black-white","perspective":"front","variation":"normal","animated":false,"extension":"png","bytes":3631,"sourceRepositoryPath":"sprites/pokemon/versions/generation-v/black-white/992.png","rightsPolicyId":"smogon-project-specific","status":"pending","originalName":"992.png","proposedName":"0992--iron-hands--generation-v-black-white--front--normal--70c2bc4e.png"},{"id":"d7cd25afdaefa63157b22ea7a686b94921c7bdb6","collection":"generation-v-black-white-shiny","perspective":"front","variation":"shiny","animated":false,"extension":"png","bytes":3586,"sourceRepositoryPath":"sprites/pokemon/versions/generation-v/black-white/shiny/992.png","rightsPolicyId":"smogon-project-specific","status":"pending","originalName":"992.png","proposedName":"0992--iron-hands--generation-v-black-white-shiny--front--shiny--d7cd25af.png"}]}
