{"schemaVersion":2,"pokemonId":"pokemon:0892-urshifu","source":{"retrievedAt":"2026-07-23","sourceRevision":"bf4c47ac82c33b330e33d98b8882d1cedb2f53e7","sourceUrls":["https://github.com/PokeAPI/sprites/tree/bf4c47ac82c33b330e33d98b8882d1cedb2f53e7","https://github.com/PokeAPI/sprites/blob/bf4c47ac82c33b330e33d98b8882d1cedb2f53e7/LICENCE.txt"],"licenseStatus":"doubtful","requiredCredits":["The Pokémon Company for official image contents, as declared by the source repository.","PokéAPI and the named community artists where a candidate comes from a fan-made collection."],"notes":["The source repository applies CC0 while also declaring image copyright owned by The Pokémon Company.","That conflict does not establish clear authority to redistribute the images in this public repository.","The repository owner explicitly directed publication of four compact battle sprites per species; rights remain doubtful and the runtime does not load them."]},"sourceUrlBase":"https://raw.githubusercontent.com/PokeAPI/sprites/bf4c47ac82c33b330e33d98b8882d1cedb2f53e7/","rightsCatalogPath":"../../../catalogs/asset-rights.json","mediaImportedCount":0,"statusSummary":{"approved":0,"pending":4,"doubtful":0,"rejected":0,"quarantined":0},"entries":[{"id":"f90b878cb877153406a97d6153d97f65954af614","collection":"other-showdown","perspective":"front","variation":"normal","animated":true,"extension":"gif","bytes":155551,"sourceRepositoryPath":"sprites/pokemon/other/showdown/892.gif","rightsPolicyId":"smogon-project-specific","status":"pending","originalName":"892.gif","proposedName":"0892--urshifu--other-showdown--front--normal--animated--f90b878c.gif"},{"id":"2208893d40ce4428048417c0dcac42cd7c1ed3b7","collection":"other-showdown-back","perspective":"back","variation":"normal","animated":true,"extension":"gif","bytes":131251,"sourceRepositoryPath":"sprites/pokemon/other/showdown/back/892.gif","rightsPolicyId":"smogon-project-specific","status":"pending","originalName":"892.gif","proposedName":"0892--urshifu--other-showdown-back--back--normal--animated--2208893d.gif"},{"id":"3a5c937f81f169b400ef43eb8fbc8fc92958bc59","collection":"other-showdown-back-shiny","perspective":"back","variation":"shiny","animated":true,"extension":"gif","bytes":122463,"sourceRepositoryPath":"sprites/pokemon/other/showdown/back/shiny/892.gif","rightsPolicyId":"smogon-project-specific","status":"pending","originalName":"892.gif","proposedName":"0892--urshifu--other-showdown-back-shiny--back--shiny--animated--3a5c937f.gif"},{"id":"4f03f7d0047314b963999ab9edc36b1787988fd6","collection":"other-showdown-shiny","perspective":"front","variation":"shiny","animated":true,"extension":"gif","bytes":149630,"sourceRepositoryPath":"sprites/pokemon/other/showdown/shiny/892.gif","rightsPolicyId":"smogon-project-specific","status":"pending","originalName":"892.gif","proposedName":"0892--urshifu--other-showdown-shiny--front--shiny--animated--4f03f7d0.gif"}]}
